<?xml version="1.0"?>
<!DOCTYPE hibernate-mapping PUBLIC "-//Hibernate/Hibernate Mapping DTD 3.0//EN"
"http://hibernate.sourceforge.net/hibernate-mapping-3.0.dtd">
<hibernate-mapping package="uk.ac.bham.cs.aam.model.impl">
    <class name="WorkDetailImpl" table="work_detail">
        <id name="id" type="integer">
            <column name="id" />
            <generator class="native" />
        </id>
        <property name="version" type="integer">
            <column name="version" />
        </property>
        <property name="startDate" type="org.jadira.usertype.dateandtime.joda.PersistentLocalDate">
            <column name="start_date" />
        </property>
        <property name="completionDate" type="org.jadira.usertype.dateandtime.joda.PersistentLocalDate">
            <column name="completion_date" />
        </property>
        <property name="description" type="string">
            <column name="description" />
        </property>
        <many-to-one name="allocation" class="WorkAllocationImpl">
            <column name="work_allocation_id" />
        </many-to-one>
    </class>
</hibernate-mapping>